mcl/__init__.py
mcl/cli.py
mcl/commands.py
mcl/config.py
mcl/executor.py
mcl_tool-0.4.1.dist-info/licenses/LICENSE
mcl_tool-0.4.1.dist-info/METADATA
mcl_tool-0.4.1.dist-info/WHEEL
mcl_tool-0.4.1.dist-info/entry_points.txt
mcl_tool-0.4.1.dist-info/top_level.txt
mcl_tool-0.4.1.dist-info/RECORD
