Metadata-Version: 2.4
Name: mcl-tool
Version: 0.4.1
Summary: My Command Line: A personal generic customizable CLI tool
Author-email: Emanuele Strazzullo <stramanu94@gmail.com>
License: MIT
Project-URL: Homepage, https://github.com/stramanu/mcl-tool
Project-URL: Repository, https://github.com/stramanu/mcl-tool
Project-URL: Documentation, https://github.com/stramanu/mcl-tool/tree/main/docs
Classifier: Programming Language :: Python :: 3
Classifier: License :: OSI Approved :: MIT License
Classifier: Operating System :: OS Independent
Classifier: Development Status :: 3 - Alpha
Requires-Python: >=3.8
License-File: LICENSE
Requires-Dist: click>=8.0
Requires-Dist: questionary>=2.0
Provides-Extra: dev
Requires-Dist: pytest>=7.0; extra == "dev"
Requires-Dist: pytest-cov; extra == "dev"
Requires-Dist: mypy; extra == "dev"
Requires-Dist: black; extra == "dev"
Requires-Dist: pre-commit; extra == "dev"
Requires-Dist: types-click; extra == "dev"
Dynamic: license-file
